setup.py
distributions_udacity_test/Binomialdistribution.py
distributions_udacity_test/Gaussiandistribution.py
distributions_udacity_test/Generaldistribution.py
distributions_udacity_test/__init__.py
distributions_udacity_test.egg-info/PKG-INFO
distributions_udacity_test.egg-info/SOURCES.txt
distributions_udacity_test.egg-info/dependency_links.txt
distributions_udacity_test.egg-info/not-zip-safe
distributions_udacity_test.egg-info/top_level.txt